License.txt
setup.py
MandalaArt.egg-info/PKG-INFO
MandalaArt.egg-info/SOURCES.txt
MandalaArt.egg-info/dependency_links.txt
MandalaArt.egg-info/requires.txt
MandalaArt.egg-info/top_level.txt
designs/__init__.py
designs/bright.py
designs/designs.py
designs/turtle_math.py
layers/__init__.py
layers/layer1.py
layers/layer2.py
layers/layer3.py
layers/layer4.py