Metadata-Version: 2.1
Name: MandalaArt
Version: 0.1.0
Summary: This is a package for generating animated mandala art using python Turtle
Home-page: https://github.com/meghc27/MandalaArt.git
Author: Megha Chakraborty
Author-email: megha.chkbrt@gmail.com
License: UNKNOWN
Platform: UNKNOWN
License-File: License.txt
